{
  "questions": [
    {
      "id": "e4-770",
      "sentence": "[戦|せん]争はよくないです。"
    },
    {
      "id": "e4-772",
      "sentence": "部屋を[散|ち]らかしてしまいました。"
    },
    {
      "id": "e4-773",
      "sentence": "公園を[散|さん]歩しました。"
    },
    {
      "id": "e4-775",
      "sentence": "[料|りょう]理を作りましたよ。"
    },
    {
      "id": "e4-776",
      "sentence": "材[料|りょう]を買いました。"
    },
    {
      "id": "e4-777",
      "sentence": "無[料|りょう]でもらいました。"
    },
    {
      "id": "e4-780",
      "sentence": "[札|ふだ]をゆっくりつけました。"
    },
    {
      "id": "e4-781",
      "sentence": "[不|ふ]注意で失敗した。"
    },
    {
      "id": "e4-783",
      "sentence": "[不|ふ]便なところに住む。"
    },
    {
      "id": "e4-785",
      "sentence": "友達とけんかして[争|あらそ]いました。"
    },
    {
      "id": "e4-787",
      "sentence": "国と国の間で[争|あらそ]いが起こる。"
    },
    {
      "id": "e4-789",
      "sentence": "校長から[令|れい]が出た。"
    },
    {
      "id": "e4-790",
      "sentence": "新しい[令|れい]和の時代が始まりました。"
    },
    {
      "id": "e4-794",
      "sentence": "テストで百点[以|い]上取りました。"
    },
    {
      "id": "e4-796",
      "sentence": "失敗したので[以|い]後気をつけます。"
    },
    {
      "id": "e4-797",
      "sentence": "競争で第一[位|い]になりました。"
    },
    {
      "id": "e4-799",
      "sentence": "社会的な地[位|い]が高い人です。"
    },
    {
      "id": "e4-802",
      "sentence": "今日は気温が[低|ひく]いです。"
    },
    {
      "id": "e4-809",
      "sentence": "これは[便|べん]利な道具のことです。"
    },
    {
      "id": "e4-811",
      "sentence": "これは[便|べん]所に行くのことです。"
    },
    {
      "id": "e4-815",
      "sentence": "手[続|つづ]きを注意深く[信|しん]ずる。"
    },
    {
      "id": "e4-817",
      "sentence": "米をゆっくり[倉|くら]に入れる。"
    },
    {
      "id": "e4-818",
      "sentence": "物をゆっくり[倉|くら]庫に置く。"
    },
    {
      "id": "e4-819",
      "sentence": "古い[倉|くら]の中身を調べました。"
    },
    {
      "id": "e4-821",
      "sentence": "注意深く[変|へん]化しました。"
    },
    {
      "id": "e4-822",
      "sentence": "次回春の[候|こう]になる。"
    },
    {
      "id": "e4-825",
      "sentence": "ともだちから本を[借|か]りました。"
    },
    {
      "id": "e4-827",
      "sentence": "友人からの[借|か]り物を返しました。"
    },
    {
      "id": "e4-828",
      "sentence": "友達で図書館で[借|か]りる。"
    },
    {
      "id": "e4-829",
      "sentence": "国語の[辞|じ]書で調べました。"
    },
    {
      "id": "e4-830",
      "sentence": "[灯|とう]台の光が見えます。"
    },
    {
      "id": "e4-832",
      "sentence": "[静|しず]かになりました。"
    },
    {
      "id": "e4-833",
      "sentence": "毎日運動して体が[健|けん]康になりました。"
    },
    {
      "id": "e4-835",
      "sentence": "[司|し]書になりました。"
    },
    {
      "id": "e4-836",
      "sentence": "読書によって[健|けん]全な心が育ちます。"
    },
    {
      "id": "e4-840",
      "sentence": "来月母の[側|そば]にいる。"
    },
    {
      "id": "e4-844",
      "sentence": "人口を表すとき[億|おく]の単位を使います。"
    },
    {
      "id": "e4-845",
      "sentence": "一[兆|ちょう]円という大きな数字です。"
    },
    {
      "id": "e4-847",
      "sentence": "春が来る[兆|ちょう]候が見えます。"
    },
    {
      "id": "e4-848",
      "sentence": "成功の大きな[兆|ちょう]しが見えてきました。"
    },
    {
      "id": "e4-850",
      "sentence": "これは学[児|どう]生活のことです。"
    },
    {
      "id": "e4-851",
      "sentence": "園[児|じ]が楽しく遊んでいます。"
    },
    {
      "id": "e4-855",
      "sentence": "これは[共|きょう]同作業のことです。"
    },
    {
      "id": "e4-856",
      "sentence": "これは公[共|きょう]の場のことです。"
    },
    {
      "id": "e4-857",
      "sentence": "これは[兵|へい]隊が行進のことです。"
    },
    {
      "id": "e4-860",
      "sentence": "これは兵[隊|たい]さんのことです。"
    },
    {
      "id": "e4-861",
      "sentence": "クラスで辞[典|てん]で調べる。"
    },
    {
      "id": "e4-862",
      "sentence": "これは古[典|てん]文学のことです。"
    },
    {
      "id": "e4-865",
      "sentence": "これは水が[冷|つめ]たいのことです。"
    },
    {
      "id": "e4-869",
      "sentence": "これは[初|はじ]めて見るのことです。"
    },
    {
      "id": "e4-871",
      "sentence": "もう一度[最初|さいしょ]からやり直します。"
    },
    {
      "id": "e4-873",
      "sentence": "これは[別|べつ]の方法のことです。"
    },
    {
      "id": "e4-874",
      "sentence": "これはお[別|わか]れするのことです。"
    },
    {
      "id": "e4-875",
      "sentence": "これは[別|べつ]々に行動のことです。"
    },
    {
      "id": "e4-876",
      "sentence": "これは特[別|べつ]な日のことです。"
    },
    {
      "id": "e4-878",
      "sentence": "これは便[利|り]な道具のことです。"
    },
    {
      "id": "e4-879",
      "sentence": "これは[利|り]用するのことです。"
    },
    {
      "id": "e4-880",
      "sentence": "これは金[利|り]が高いのことです。"
    },
    {
      "id": "e4-881",
      "sentence": "本をゆっくり[刷|さつ]る。"
    },
    {
      "id": "e4-882",
      "sentence": "学校のきかいで印[刷|さつ]しました。"
    },
    {
      "id": "e4-883",
      "sentence": "これは[刷|さつ]り上がりのことです。"
    },
    {
      "id": "e4-884",
      "sentence": "これは新[刷|さつ]の本のことです。"
    },
    {
      "id": "e4-885",
      "sentence": "お母さんはPTAの[副|ふく]会長です。"
    },
    {
      "id": "e4-886",
      "sentence": "国語の[副|ふく]読本を使って勉強します。"
    },
    {
      "id": "e4-887",
      "sentence": "薬の[副|ふく]作用について調べました。"
    },
    {
      "id": "e4-890",
      "sentence": "これは成[功|こう]するのことです。"
    },
    {
      "id": "e4-893",
      "sentence": "今度仲間に[加|くわ]わる。"
    },
    {
      "id": "e4-895",
      "sentence": "これは参[加|か]するのことです。"
    },
    {
      "id": "e4-897",
      "sentence": "これは[努|ど]力するのことです。"
    },
    {
      "id": "e4-906",
      "sentence": "これは[勇|いさ]ましいのことです。"
    },
    {
      "id": "e4-909",
      "sentence": "プレゼントを[包|つつ]む。"
    },
    {
      "id": "e4-910",
      "sentence": "きれいな紙で[包|つつ]むを使いました。"
    },
    {
      "id": "e4-911",
      "sentence": "プレゼントをきれいな[包|ほう]そう紙でつつみました。"
    },
    {
      "id": "e4-912",
      "sentence": "来月愛に[包|つつ]まれる。"
    },
    {
      "id": "e4-913",
      "sentence": "学校を注意深く[卒|そつ]業。"
    },
    {
      "id": "e4-914",
      "sentence": "春に[卒|そつ]業式が行われます。"
    },
    {
      "id": "e4-916",
      "sentence": "多くの[卒|そつ]業生が集まりました。"
    },
    {
      "id": "e4-922",
      "sentence": "英語の[単|たん]語を覚えました。"
    },
    {
      "id": "e4-925",
      "sentence": "国立[博|はく]物館を見学しました。"
    },
    {
      "id": "e4-931",
      "sentence": "赤い旗を目[印|じるし]にしました。"
    },
    {
      "id": "e4-932",
      "sentence": "パンフレットを[印|いん]刷しました。"
    },
    {
      "id": "e4-933",
      "sentence": "重要な会議に[参|さん]加しました。"
    },
    {
      "id": "e4-934",
      "sentence": "勉強の[参|さん]考書を買いました。"
    }
  ]
}
