{
  "questions": [
    {
      "id": "e5-477",
      "sentence": "[険|けん]しい道を登りました。"
    },
    {
      "id": "e5-481",
      "sentence": "こうせきをたたえ[賛|さん]しました。"
    },
    {
      "id": "e5-482",
      "sentence": "[迷|まよ]い道に入りましたよ。"
    },
    {
      "id": "e5-483",
      "sentence": "ここは[険|けわ]しい土地です。"
    },
    {
      "id": "e5-485",
      "sentence": "[舎|しゃ]人になりました。"
    },
    {
      "id": "e5-486",
      "sentence": "[資|し]げんを有効につかいました。"
    },
    {
      "id": "e5-488",
      "sentence": "[迷|まよ]いばしをしました。"
    },
    {
      "id": "e5-489",
      "sentence": "[険|けん]しくそびえています。"
    },
    {
      "id": "e5-491",
      "sentence": "学[舎|しゃ]で学びました。"
    },
    {
      "id": "e5-492",
      "sentence": "[資|し]ざいを活用しました。"
    },
    {
      "id": "e5-493",
      "sentence": "[賛|さん]成意見が多いです。"
    },
    {
      "id": "e5-496",
      "sentence": "[綿|めん]実油を使いました。"
    },
    {
      "id": "e5-497",
      "sentence": "仮[舎|しゃ]を建てました。"
    },
    {
      "id": "e5-498",
      "sentence": "[資|し]本けになりました。"
    },
    {
      "id": "e5-499",
      "sentence": "[賛|さん]成者が多いです。"
    },
    {
      "id": "e5-500",
      "sentence": "[迷|まよ]いが生じました。"
    },
    {
      "id": "e5-501",
      "sentence": "[険|けん]あくな目つきです。"
    },
    {
      "id": "e5-502",
      "sentence": "[綿|わた]入れを作りました。"
    },
    {
      "id": "e5-503",
      "sentence": "校[舎|しゃ]を改築しました。"
    },
    {
      "id": "e5-504",
      "sentence": "[資|し]格試験を受けました。"
    },
    {
      "id": "e5-505",
      "sentence": "[賛|さん]どうしゃをつのりました。"
    },
    {
      "id": "e5-508",
      "sentence": "[綿|めん]織物を作りました。"
    },
    {
      "id": "e5-510",
      "sentence": "[資|し]かくを取りました。"
    },
    {
      "id": "e5-511",
      "sentence": "[賛|さん]びのこえがあがりました。"
    },
    {
      "id": "e5-512",
      "sentence": "[迷|まよ]ってしまいました。"
    },
    {
      "id": "e5-513",
      "sentence": "[険|けん]しい山をめざしました。"
    },
    {
      "id": "e5-514",
      "sentence": "[綿|わた]ぼうしが飛びました。"
    },
    {
      "id": "e5-516",
      "sentence": "[資|し]りょうをあつめました。"
    },
    {
      "id": "e5-517",
      "sentence": "[賛|さん]ひをきめました。"
    },
    {
      "id": "e5-518",
      "sentence": "みちに[迷|まよ]って出口を見つけました。"
    },
    {
      "id": "e5-519",
      "sentence": "[険|けん]路を進みました。"
    },
    {
      "id": "e5-520",
      "sentence": "[綿|めん]羊を飼いました。"
    },
    {
      "id": "e5-522",
      "sentence": "[資|し]ほんの大切さをまなびました。"
    },
    {
      "id": "e5-523",
      "sentence": "[賛|さん]せいひょうを入れました。"
    },
    {
      "id": "e5-525",
      "sentence": "[険|けん]しい顔つきです。"
    },
    {
      "id": "e5-526",
      "sentence": "ここは[綿|めん]の工場です。"
    },
    {
      "id": "e5-528",
      "sentence": "[資|し]産管理をしました。"
    },
    {
      "id": "e5-529",
      "sentence": "[賛|さん]じょきんを出しました。"
    },
    {
      "id": "e5-531",
      "sentence": "[険|けん]しい山の地たいです。"
    },
    {
      "id": "e5-532",
      "sentence": "[綿|わた]くずを集めました。"
    },
    {
      "id": "e5-534",
      "sentence": "[資|し]ざいのうんようほうほうをまなびました。"
    },
    {
      "id": "e5-536",
      "sentence": "[迷|まよ]いを断ちました。"
    },
    {
      "id": "e5-537",
      "sentence": "会議室は[険|けん]悪な空気です。"
    },
    {
      "id": "e5-538",
      "sentence": "[綿|めん]球を使いました。"
    },
    {
      "id": "e5-540",
      "sentence": "[資|し]げんかつようのじゅうようせいをりかいしました。"
    },
    {
      "id": "e5-546",
      "sentence": "[資|し]げんかいはつにとりくみました。"
    },
    {
      "id": "e5-547",
      "sentence": "[賛|さん]同を求めました。"
    },
    {
      "id": "e5-548",
      "sentence": "[迷|まよ]い道を明らかにしました。"
    },
    {
      "id": "e5-552",
      "sentence": "[資|し]げんのせつやくをこころがけました。"
    },
    {
      "id": "e5-554",
      "sentence": "[迷|まよ]い鳥が来ました。"
    },
    {
      "id": "e5-555",
      "sentence": "[険|けん]悪な関係を解説しました。"
    },
    {
      "id": "e5-557",
      "sentence": "[舎|しゃ]外に出について述べました。"
    },
    {
      "id": "e5-558",
      "sentence": "[資|し]ほんしゅぎのしくみをべんきょうしました。"
    },
    {
      "id": "e5-561",
      "sentence": "[険|けん]しい目をしました。"
    },
    {
      "id": "e5-564",
      "sentence": "[資|し]げんもんだいについてかんがえました。"
    },
    {
      "id": "e5-565",
      "sentence": "[賛|さん]成者が増えました。"
    },
    {
      "id": "e5-566",
      "sentence": "[迷|まよ]いが晴れました。"
    },
    {
      "id": "e5-568",
      "sentence": "[綿|わた]打ちをしました。"
    },
    {
      "id": "e5-569",
      "sentence": "館[舎|しゃ]を見学しました。"
    },
    {
      "id": "e5-572",
      "sentence": "[迷|めい]案を出しました。"
    },
    {
      "id": "e5-574",
      "sentence": "[綿|めん]100%を説明しました。"
    },
    {
      "id": "e5-575",
      "sentence": "[舎|しゃ]内を案内しました。"
    },
    {
      "id": "e5-576",
      "sentence": "[資|し]料を調べました。"
    },
    {
      "id": "e5-578",
      "sentence": "[迷|まよ]いなく進みました。"
    },
    {
      "id": "e5-579",
      "sentence": "[険|けん]しい道程について語りました。"
    },
    {
      "id": "e5-581",
      "sentence": "[舎|しゃ]利容器を作りました。"
    },
    {
      "id": "e5-582",
      "sentence": "[資|し]料集めに協力しました。"
    },
    {
      "id": "e5-586",
      "sentence": "重大な[綿|めん]織工場です。"
    },
    {
      "id": "e5-588",
      "sentence": "[資|し]金を準備しました。"
    },
    {
      "id": "e5-589",
      "sentence": "[賛|さん]助会員になりました。"
    },
    {
      "id": "e5-591",
      "sentence": "[険|けん]しい岩山について話しました。"
    },
    {
      "id": "e5-594",
      "sentence": "[資|し]格を取るために勉強しました。"
    },
    {
      "id": "e5-595",
      "sentence": "[賛|さん]成投票をしました。"
    },
    {
      "id": "e5-597",
      "sentence": "[険|けん]悪な顔つきです。"
    },
    {
      "id": "e5-599",
      "sentence": "別[舎|しゃ]を建てました。"
    },
    {
      "id": "e5-601",
      "sentence": "[賛|さん]美歌集を作りました。"
    },
    {
      "id": "e5-602",
      "sentence": "[迷|まよ]い人になりました。"
    },
    {
      "id": "e5-605",
      "sentence": "[舎|しゃ]屋を建てました。"
    },
    {
      "id": "e5-606",
      "sentence": "[資|し]料の整理をしました。"
    },
    {
      "id": "e5-610",
      "sentence": "[綿|めん]素材を選びました。"
    },
    {
      "id": "e5-614",
      "sentence": "しばらく前に[評|ひょう]することができました。"
    },
    {
      "id": "e5-616",
      "sentence": "[講|こう]演会に行きました。"
    },
    {
      "id": "e5-617",
      "sentence": "[講|こう]義を聞きました。"
    },
    {
      "id": "e5-619",
      "sentence": "先日感[謝|しゃ]することができました。"
    },
    {
      "id": "e5-620",
      "sentence": "前日[識|しき]することができました。"
    },
    {
      "id": "e5-621",
      "sentence": "知[識|しき]を深めました。"
    },
    {
      "id": "e5-622",
      "sentence": "この前[護|ご]することができました。"
    },
    {
      "id": "e5-624",
      "sentence": "[豊|ゆた]かな生活について述べました。"
    },
    {
      "id": "e5-625",
      "sentence": "[豊|ほう]作を説明しました。"
    },
    {
      "id": "e5-626",
      "sentence": "[財|ざい]産を管理しました。"
    },
    {
      "id": "e5-627",
      "sentence": "[財|ざい]布を買いました。"
    },
    {
      "id": "e5-907",
      "sentence": "[質|しつ]問をしました。"
    },
    {
      "id": "e5-913",
      "sentence": "[評|ひょう]判を聞きました。"
    },
    {
      "id": "e5-924",
      "sentence": "[夢|ゆめ]と現実の間で生きる"
    },
    {
      "id": "e5-927",
      "sentence": "[適応|てきおう]して生きる力"
    },
    {
      "id": "e5-930",
      "sentence": "[事件|じけん]の真実を知る"
    },
    {
      "id": "e5-933",
      "sentence": "[再生|さいせい]と修復を行う"
    },
    {
      "id": "e5-936",
      "sentence": "[姿勢|しせい]を正確に保つ"
    },
    {
      "id": "e5-940",
      "sentence": "[型紙|かたがみ]で服を作る"
    },
    {
      "id": "e5-945",
      "sentence": "[任|まか]せて安心する"
    },
    {
      "id": "e5-953",
      "sentence": "[表情|ひょうじょう]を見て判断"
    },
    {
      "id": "e5-960",
      "sentence": "[質|しつ]問を準備する"
    },
    {
      "id": "e5-967",
      "sentence": "[燃料|ねんりょう]を入れて進む"
    },
    {
      "id": "e5-974",
      "sentence": "[賞|しょう]状を大切に保管"
    },
    {
      "id": "e5-982",
      "sentence": "[物質|ぶっしつ]の構造を知る"
    },
    {
      "id": "e5-990",
      "sentence": "[技|ぎ]術を学ぶ授業"
    }
  ]
}
