{
  "questions": [
    {
      "id": "sen-423",
      "sentence": "[立証|りっしょう]することができました。"
    },
    {
      "id": "sen-424",
      "sentence": "[論拠|ろんきょ]を示しました。"
    },
    {
      "id": "sen-425",
      "sentence": "[根拠|こんきょ]があります。"
    },
    {
      "id": "sen-426",
      "sentence": "[理由|りゆう]を説明しました。"
    },
    {
      "id": "sen-427",
      "sentence": "[原因|げんいん]を突き止めました。"
    },
    {
      "id": "sen-428",
      "sentence": "[要因|よういん]を分析しました。"
    },
    {
      "id": "sen-429",
      "sentence": "[素因|そいん]があります。"
    },
    {
      "id": "sen-430",
      "sentence": "[誘因|ゆういん]となりました。"
    },
    {
      "id": "sen-431",
      "sentence": "[契機|けいき]となりました。"
    },
    {
      "id": "sen-432",
      "sentence": "[動機|どうき]を確認しました。"
    },
    {
      "id": "sen-433",
      "sentence": "[意図|いと]を理解しました。"
    },
    {
      "id": "sen-434",
      "sentence": "[意向|いこう]を尊重します。"
    },
    {
      "id": "sen-435",
      "sentence": "[意志|いし]を貫きます。"
    },
    {
      "id": "sen-436",
      "sentence": "[意欲|いよく]を燃やします。"
    },
    {
      "id": "sen-437",
      "sentence": "[熱意|ねつい]を持ちます。"
    },
    {
      "id": "sen-438",
      "sentence": "[情熱|じょうねつ]を注ぎます。"
    },
    {
      "id": "sen-439",
      "sentence": "[熱望|ねつぼう]しています。"
    },
    {
      "id": "sen-440",
      "sentence": "[渇望|かつぼう]しています。"
    },
    {
      "id": "sen-441",
      "sentence": "[切望|せつぼう]しています。"
    },
    {
      "id": "sen-442",
      "sentence": "[願望|がんぼう]を抱いています。"
    },
    {
      "id": "sen-443",
      "sentence": "[要望|ようぼう]をお聞きします。"
    },
    {
      "id": "sen-444",
      "sentence": "[要求|ようきゅう]にお応えします。"
    },
    {
      "id": "sen-445",
      "sentence": "[要請|ようせい]を受けました。"
    },
    {
      "id": "sen-446",
      "sentence": "[依頼|いらい]されました。"
    },
    {
      "id": "sen-447",
      "sentence": "[委託|いたく]されました。"
    },
    {
      "id": "sen-448",
      "sentence": "[委任|いにん]されました。"
    },
    {
      "id": "sen-449",
      "sentence": "[任命|にんめい]されました。"
    },
    {
      "id": "sen-450",
      "sentence": "[指名|しめい]されました。"
    },
    {
      "id": "sen-451",
      "sentence": "[選出|せんしゅつ]されました。"
    },
    {
      "id": "sen-452",
      "sentence": "[選択|せんたく]しました。"
    },
    {
      "id": "sen-453",
      "sentence": "[選別|せんべつ]しました。"
    },
    {
      "id": "sen-454",
      "sentence": "[抽出|ちゅうしゅつ]しました。"
    },
    {
      "id": "sen-455",
      "sentence": "[抽選|ちゅうせん]で決めました。"
    },
    {
      "id": "sen-456",
      "sentence": "[決定|けってい]しました。"
    },
    {
      "id": "sen-457",
      "sentence": "[決断|けつだん]しました。"
    },
    {
      "id": "sen-458",
      "sentence": "[決意|けつい]を固めましたよ。"
    },
    {
      "id": "sen-459",
      "sentence": "[決心|けっしん]しました。"
    },
    {
      "id": "sen-460",
      "sentence": "[覚悟|かくご]を決めました。"
    },
    {
      "id": "sen-461",
      "sentence": "[腹|はら]を決めました。"
    },
    {
      "id": "sen-462",
      "sentence": "[胸|むね]を張って歩きます。"
    },
    {
      "id": "sen-463",
      "sentence": "[肩|かた]の荷が下りました。"
    },
    {
      "id": "sen-464",
      "sentence": "[足|あし]取り軽く進みます。"
    },
    {
      "id": "sen-465",
      "sentence": "[頭|あたま]を使って考えます。"
    },
    {
      "id": "sen-466",
      "sentence": "[手|て]に職をつけたいです。"
    },
    {
      "id": "sen-467",
      "sentence": "[目|め]標を定めました。"
    },
    {
      "id": "sen-468",
      "sentence": "[耳|みみ]を傾けて聞きます。"
    },
    {
      "id": "sen-469",
      "sentence": "[口|くち]に出して言います。"
    },
    {
      "id": "sen-470",
      "sentence": "[心|こころ]を込めて作ります。"
    },
    {
      "id": "sen-471",
      "sentence": "[身|み]を粉にして働きます。"
    },
    {
      "id": "sen-472",
      "sentence": "[骨|ほね]身を惜しみません。"
    },
    {
      "id": "sen-473",
      "sentence": "[血|ち]の滲む努力をします。"
    },
    {
      "id": "sen-474",
      "sentence": "[汗|あせ]水流して働きます。"
    },
    {
      "id": "sen-475",
      "sentence": "[涙|なみだ]ぐましい努力をします。"
    },
    {
      "id": "sen-476",
      "sentence": "[笑顔|えがお]を絶やしません。"
    },
    {
      "id": "sen-477",
      "sentence": "[微笑|ほほえ]みを浮かべます。"
    },
    {
      "id": "sen-478",
      "sentence": "[歓喜|かんき]に包まれました。"
    },
    {
      "id": "sen-479",
      "sentence": "[喜悦|きえつ]を感じます。"
    },
    {
      "id": "sen-480",
      "sentence": "[歓楽|かんらく]の時を過ごしました。"
    },
    {
      "id": "sen-481",
      "sentence": "[快楽|かいらく]を求めません。"
    },
    {
      "id": "sen-482",
      "sentence": "[享楽|きょうらく]に溺れません。"
    },
    {
      "id": "sen-483",
      "sentence": "[安楽|あんらく]な生活を送ります。"
    },
    {
      "id": "sen-484",
      "sentence": "[楽観|らっかん]的に考えます。"
    },
    {
      "id": "sen-485",
      "sentence": "[悲観|ひかん]しません。"
    },
    {
      "id": "sen-486",
      "sentence": "[希望|きぼう]を失いません。"
    },
    {
      "id": "sen-487",
      "sentence": "[絶望|ぜつぼう]しません。"
    },
    {
      "id": "sen-488",
      "sentence": "[失望|しつぼう]しません。"
    },
    {
      "id": "sen-489",
      "sentence": "[落胆|らくたん]しません。"
    },
    {
      "id": "sen-490",
      "sentence": "[落込|おちこ]みません。"
    },
    {
      "id": "sen-491",
      "sentence": "[沈滞|ちんたい]しません。"
    },
    {
      "id": "sen-492",
      "sentence": "[停滞|ていたい]しません。"
    },
    {
      "id": "sen-493",
      "sentence": "[前進|ぜんしん]し続けます。"
    },
    {
      "id": "sen-494",
      "sentence": "[進歩|しんぽ]を続けます。"
    },
    {
      "id": "sen-495",
      "sentence": "[発展|はってん]を目指しました。"
    },
    {
      "id": "sen-496",
      "sentence": "[成長|せいちょう]し続けます。"
    },
    {
      "id": "sen-497",
      "sentence": "[向上|こうじょう]心を持ちます。"
    },
    {
      "id": "sen-498",
      "sentence": "[改良|かいりょう]を重ねます。"
    },
    {
      "id": "sen-499",
      "sentence": "[改善|かいぜん]に努めました。"
    },
    {
      "id": "sen-500",
      "sentence": "[完成|かんせい]を目指しました。"
    },
    {
      "id": "sen-501",
      "sentence": "[哲|てつ]学的な思考をします。"
    },
    {
      "id": "sen-502",
      "sentence": "[哲|てつ]学的な思考をしました。"
    },
    {
      "id": "sen-503",
      "sentence": "[哲|てつ]学を学んでいます。"
    },
    {
      "id": "sen-504",
      "sentence": "[哲|てつ]学を学んでいました。"
    },
    {
      "id": "sen-505",
      "sentence": "[人|よみ]の概念を理解しました。"
    },
    {
      "id": "sen-506",
      "sentence": "[人|よみ]の概念を理解しましたよ。"
    },
    {
      "id": "sen-507",
      "sentence": "[間|よみ]の重要性を認識しています。"
    },
    {
      "id": "sen-508",
      "sentence": "[間|よみ]について深く考察します。"
    },
    {
      "id": "sen-509",
      "sentence": "価値の[存|そん]在を認めます。"
    },
    {
      "id": "sen-510",
      "sentence": "[存|そん]在の意味を考えます。"
    },
    {
      "id": "sen-511",
      "sentence": "[存|そん]在の意味を考えました。"
    },
    {
      "id": "sen-512",
      "sentence": "価値の[存|そん]在を認めました。"
    },
    {
      "id": "sen-513",
      "sentence": "現[在|ざい]の状況を分析します。"
    },
    {
      "id": "sen-514",
      "sentence": "存[在|ざい]意義を見つけます。"
    },
    {
      "id": "sen-515",
      "sentence": "存[在|ざい]意義を見つけました。"
    },
    {
      "id": "sen-516",
      "sentence": "現[在|ざい]の状況を分析しました。"
    },
    {
      "id": "sen-517",
      "sentence": "[義|よみ]の概念を理解しました。"
    },
    {
      "id": "sen-518",
      "sentence": "[義|よみ]の重要性を認識しています。"
    },
    {
      "id": "sen-519",
      "sentence": "[義|よみ]について深く考察します。"
    },
    {
      "id": "sen-520",
      "sentence": "新しい方法を[探|さが]します。"
    },
    {
      "id": "sen-521",
      "sentence": "真理を[探|たん]究します。"
    },
    {
      "id": "sen-522",
      "sentence": "新しい方法を[探|さが]しました。"
    },
    {
      "id": "sen-523",
      "sentence": "真理を[探|たん]究しました。"
    },
    {
      "id": "sen-524",
      "sentence": "[究|よみ]の重要性を認識しています。"
    },
    {
      "id": "sen-525",
      "sentence": "[究|よみ]の重要性を認識していました。"
    },
    {
      "id": "sen-526",
      "sentence": "[問|と]いかけを続けます。"
    },
    {
      "id": "sen-527",
      "sentence": "重要な[問|もん]題を扱います。"
    },
    {
      "id": "sen-528",
      "sentence": "重要な[問|もん]題を扱いました。"
    },
    {
      "id": "sen-529",
      "sentence": "重要な[問|もん]題が扱います。"
    },
    {
      "id": "sen-530",
      "sentence": "[憲|けん]政の理念を理解します。"
    },
    {
      "id": "sen-531",
      "sentence": "[憲|けん]政の理念を理解しました。"
    },
    {
      "id": "sen-532",
      "sentence": "[憲|けん]法を学習しました。"
    },
    {
      "id": "sen-533",
      "sentence": "[憲|けん]法を学習しましたよ。"
    },
    {
      "id": "sen-534",
      "sentence": "[政|よみ]について深く考察します。"
    },
    {
      "id": "sen-535",
      "sentence": "[政|よみ]について深く考察しました。"
    },
    {
      "id": "sen-536",
      "sentence": "[政|よみ]の概念を理解しました。"
    },
    {
      "id": "sen-537",
      "sentence": "[常|つね]に努力しています。"
    },
    {
      "id": "sen-538",
      "sentence": "[常|じょう]識を身につけます。"
    },
    {
      "id": "sen-539",
      "sentence": "[常|じょう]識を身につけました。"
    },
    {
      "id": "sen-540",
      "sentence": "[常|じょう]識が身につけます。"
    },
    {
      "id": "sen-541",
      "sentence": "武[道|ぶどう]の精神を学びます。"
    },
    {
      "id": "sen-542",
      "sentence": "正しい[道|みち]を歩みます。"
    },
    {
      "id": "sen-543",
      "sentence": "武[道|ぶどう]の精神を学びました。"
    },
    {
      "id": "sen-544",
      "sentence": "正しい[道|みち]を歩みました。"
    },
    {
      "id": "sen-545",
      "sentence": "規[則|そく]に従います。"
    },
    {
      "id": "sen-546",
      "sentence": "法[則|そく]を発見しました。"
    },
    {
      "id": "sen-547",
      "sentence": "法[則|そく]を発見しましたよ。"
    },
    {
      "id": "sen-548",
      "sentence": "規[則|そく]に従いました。"
    },
    {
      "id": "sen-549",
      "sentence": "[議|よみ]について深く考察します。"
    },
    {
      "id": "sen-550",
      "sentence": "[議|よみ]の重要性を認識しています。"
    },
    {
      "id": "sen-551",
      "sentence": "[議|よみ]の重要性を認識していました。"
    },
    {
      "id": "sen-552",
      "sentence": "[制|よみ]の重要性を認識しています。"
    },
    {
      "id": "sen-553",
      "sentence": "[制|よみ]の概念を理解しました。"
    },
    {
      "id": "sen-554",
      "sentence": "制[度|ど]を改革します。"
    },
    {
      "id": "sen-555",
      "sentence": "態[度|ど]を改めます。"
    },
    {
      "id": "sen-556",
      "sentence": "態[度|ど]を改めました。"
    },
    {
      "id": "sen-557",
      "sentence": "態[度|ど]が改めます。"
    },
    {
      "id": "sen-558",
      "sentence": "[擁|よみ]の重要性を認識しています。"
    },
    {
      "id": "sen-559",
      "sentence": "[擁|よみ]の重要性を認識していました。"
    },
    {
      "id": "sen-560",
      "sentence": "[擁|よみ]の概念を理解しました。"
    },
    {
      "id": "sen-561",
      "sentence": "[擁|よみ]について深く考察します。"
    },
    {
      "id": "sen-562",
      "sentence": "[護|よみ]について深く考察します。"
    },
    {
      "id": "sen-563",
      "sentence": "[護|よみ]について深く考察しました。"
    },
    {
      "id": "sen-564",
      "sentence": "[護|よみ]へついて深く考察します。"
    },
    {
      "id": "sen-565",
      "sentence": "この[護|よみ]について深く考察します。"
    },
    {
      "id": "sen-566",
      "sentence": "[量|りょう]子力学を学びます。"
    },
    {
      "id": "sen-567",
      "sentence": "[量|りょう]子力学を学びました。"
    },
    {
      "id": "sen-568",
      "sentence": "[量|りょう]子力学が学びます。"
    }
  ]
}
